LICENSE
MANIFEST.in
README.md
Requirements.txt
setup.py
examples/README.md
examples/TMIDI_Processor_Examples.py
examples/efficient_virtuoso.py
examples/intelligent_virtuoso.py
examples/karaoke_master.py
examples/midi_mir_statistics.py
examples/midi_search.py
examples/superpiano5_(reformer_tpu).py
tegridy_raspberry/README.md
tegridy_raspberry/keras/Keras4Raspberry.sh
tegridy_raspberry/keras/README.md
tegridy_raspberry/numpy/Numpy4Raspberry.sh
tegridy_raspberry/numpy/README.md
tegridy_raspberry/pyknon/MidiFile.py
tegridy_raspberry/pyknon/README.md
tegridy_raspberry/pyknon/___init.py___
tegridy_raspberry/pyknon/genmidi.py
tegridy_raspberry/pyknon/music.py
tegridy_raspberry/pyknon/notation.py
tegridy_raspberry/pyknon/pc_sets.py
tegridy_raspberry/pyknon/pcset.py
tegridy_raspberry/pyknon/plot.py
tegridy_raspberry/pyknon/simplemusic.py
tegridy_raspberry/pytorch/PyTorch4Raspbery.sh
tegridy_raspberry/pytorch/README.md
tegridy_raspberry/tensorflow/README.md
tegridy_raspberry/tensorflow/Tensorflow4Raspberry.sh
tegridy_tools/MIDI.py
tegridy_tools/README.md
tegridy_tools/TMIDI.py
tegridy_tools/__init__.py
tegridy_tools/__version__.py
tegridy_tools/markovify.py
tegridy_tools/minGPT.py
tegridy_tools/seed.mid
tegridy_tools.egg-info/PKG-INFO
tegridy_tools.egg-info/SOURCES.txt
tegridy_tools.egg-info/dependency_links.txt
tegridy_tools.egg-info/namespace_packages.txt
tegridy_tools.egg-info/not-zip-safe
tegridy_tools.egg-info/requires.txt
tegridy_tools.egg-info/top_level.txt
tegridy_tools/__pycache__/markovify.cpython-37.pyc
tegridy_tools/docs/README.md
tegridy_tools/docs/TMIDI.TXT
tegridy_tools/markovify/README.md
tegridy_tools/markovify/markovify-0.8.3.zip
tegridy_tools/markovify/markovify-master.zip
tegridy_tools/markovify/markovify.py
tegridy_tools/mido/README.md
tegridy_tools/mido/mido-1.2.9.zip
tegridy_tools/mido/mido-master.zip
tegridy_tools/minGPT/README.md
tegridy_tools/minGPT/minGPT.py
tegridy_tools/notebooks/Advanced_MIDI_Channel_Splitter.ipynb
tegridy_tools/notebooks/Advanced_MIDI_Silence_Removal_Tool.ipynb
tegridy_tools/notebooks/MIDI_Chords_Progressions_Generator.ipynb
tegridy_tools/notebooks/MIDI_MIR_Statistics.ipynb
tegridy_tools/notebooks/MIDI_Search.ipynb
tegridy_tools/notebooks/README.md
