Metadata-Version: 2.1
Name: tegridy-tools
Version: 1.0.2
Summary: All tegridy-tools as python modules because there is never enough tegridy :)
Home-page: https://github.com/asigalov61/tegridy-tools
Author: Aleksandr Sigalov
Author-email: asigalov61@hotmail.com
License: Apache 2.0
Keywords: music nlp raspberry-pi machine-learning deep-learning midi numpy               keras pytorch music-generation python-modules plagiarism-detection               midi-toolkit midi-processing artifical-intelligence tensorflow2               tegridy pyknon midi-processor midi-search
Platform: UNKNOWN
Classifier: Development Status :: 5 - Production/Stable
Classifier: Intended Audience :: Science/Research
Classifier: License :: OSI Approved :: Apache Software License
Classifier: Operating System :: OS Independent
Classifier: Programming Language :: Python :: 3.4
Classifier: Programming Language :: Python :: 3.5
Classifier: Programming Language :: Python :: 3.6
Classifier: Programming Language :: Python :: 3.7
Classifier: Programming Language :: Python :: 3.8
Classifier: Programming Language :: Python :: 3.9
